discordiapy/__init__.py
discordiapy/client.py
DiscordiaPy-0.1.0.dist-info/LICENSE
DiscordiaPy-0.1.0.dist-info/METADATA
DiscordiaPy-0.1.0.dist-info/WHEEL
DiscordiaPy-0.1.0.dist-info/top_level.txt
DiscordiaPy-0.1.0.dist-info/RECORD
