Metadata-Version: 2.1
Name: DiscordiaPy
Version: 0.1.0
Summary: A simple Discord API wrapper for Discord's api.
Author: shvrs
License: MIT
Project-URL: Homepage, https://github.com/shvrs/DiscordiaPy
Project-URL: Source, https://github.com/shvrs/DiscordiaPy
Project-URL: Tracker, https://github.com/shvrs/DiscordiaPy/issues
Classifier: Programming Language :: Python :: 3
Classifier: License :: OSI Approved :: MIT License
Classifier: Operating System :: OS Independent
Classifier: Intended Audience :: Developers
Classifier: Topic :: Software Development :: Libraries :: Python Modules
Requires-Python: >=3.7
License-File: LICENSE
Requires-Dist: requests
Provides-Extra: dev
Requires-Dist: black ; extra == 'dev'
Requires-Dist: pytest ; extra == 'dev'
